cidp/KubernetesController.py
cidp/SparkSessionBuilder.py
cidp/__init__.py
cidp/kube.py
cidp/kubernetes.py
cidp/spark.py
cidp-0.0.6.dist-info/METADATA
cidp-0.0.6.dist-info/WHEEL
cidp-0.0.6.dist-info/top_level.txt
cidp-0.0.6.dist-info/RECORD
