Metadata-Version: 2.1
Name: cidp
Version: 0.0.6
Summary: CIDP Python SDK
Home-page: https://gitlab.cidp.io/common/pypi/cidp
Author: mccho
Author-email: skt.mccho@sk.com
Classifier: Programming Language :: Python :: 3
Classifier: License :: OSI Approved :: MIT License
Classifier: Operating System :: OS Independent
Requires-Python: >=3.6
